examples/__init__.py
interstate75wrapper/__init__.py
interstate75wrapper/baseinterstate75.py
interstate75wrapper/datetime.py
interstate75wrapper/display_type.py
interstate75wrapper/mockinterstate75.py
interstate75wrapper/nativeinterstate75.py
interstate75wrapper/pen.py
interstate75wrapper/pygame_graphics.py
interstate75_wrapper-0.2.0.dist-info/LICENSE
interstate75_wrapper-0.2.0.dist-info/METADATA
interstate75_wrapper-0.2.0.dist-info/WHEEL
interstate75_wrapper-0.2.0.dist-info/top_level.txt
interstate75_wrapper-0.2.0.dist-info/RECORD
