Metadata-Version: 2.1
Name: interstate75-wrapper
Version: 0.2.0
Summary: A wrapper around Pimoroni's `interstate75` library which allows for running locally and easier testing.
Home-page: https://github.com/andrewjw/interstate75-wrapper
Author: Andrew Wilkinson
Author-email: andrewjwilkinson@gmail.com
Classifier: Programming Language :: Python :: 3.8
Classifier: Programming Language :: Python :: 3.9
Classifier: Programming Language :: Python :: 3.10
Classifier: Programming Language :: Python :: 3.11
Classifier: License :: OSI Approved :: GNU General Public License v3 (GPLv3)
Classifier: Operating System :: OS Independent
Requires-Python: >=3.8
License-File: LICENSE
Requires-Dist: pycodestyle (==2.11.0)
Requires-Dist: coveralls (==3.3.1)
Requires-Dist: pygame (==2.5.0)
Requires-Dist: python-semantic-release (==7.34.6)
Requires-Dist: mypy (==1.4.1)
Requires-Dist: wheel (==0.41.0)
Requires-Dist: micropython-rp2-pico-stubs (==1.20.0.post2)
Requires-Dist: adafruit-ampy (==1.1.0)
